django_routes/__init__.py
django_routes/apps.py
django_routes/routers.py
django_routes/settings.py
django_routes/urls.py
django_routes/version.py
django_routes/views.py
django_routes/viewsets.py
django_routes/helpers/__init__.py
django_routes/helpers/button.py
django_routes/helpers/permission.py
django_routes/helpers/url.py
django_routes/templatetags/__init__.py
django_routes/templatetags/routes_tags.py
django_routes-0.1.3.dist-info/METADATA
django_routes-0.1.3.dist-info/WHEEL
django_routes-0.1.3.dist-info/top_level.txt
django_routes-0.1.3.dist-info/RECORD
