Metadata-Version: 2.1
Name: django-routes
Version: 0.1.3
Summary: Django Routes
Home-page: https://github.com/realnoobs/django_routes
Author: Rizki Sasri Dwitama
Author-email: sasri.project@gmail.com
License: MIT
Project-URL: Documentation, https://github.com/realnoobs/django_routes
Project-URL: Source, https://github.com/realnoobs/django_routes
Platform: UNKNOWN
Classifier: Environment :: Web Environment
Classifier: Framework :: Django
Classifier: Intended Audience :: Developers
Classifier: License :: OSI Approved :: MIT License
Classifier: Operating System :: OS Independent
Classifier: Programming Language :: Python
Classifier: Programming Language :: Python :: 3
Classifier: Programming Language :: Python :: 3 :: Only
Classifier: Programming Language :: Python :: 3.8
Classifier: Programming Language :: Python :: 3.9
Classifier: Topic :: Internet :: WWW/HTTP
Classifier: Topic :: Internet :: WWW/HTTP :: Dynamic Content
Classifier: Topic :: Internet :: WWW/HTTP :: WSGI
Classifier: Topic :: Software Development :: Libraries :: Python Modules
Classifier: Topic :: Software Development :: Libraries :: Application Frameworks
Requires-Python: >=3.6
Requires-Dist: django (<4.0,>=3.2.7)
Requires-Dist: django-hookup
Requires-Dist: django-filter
Provides-Extra: allauth
Requires-Dist: django-allauth ; extra == 'allauth'
